doc_page_extractor/__init__.py
doc_page_extractor/check_env.py
doc_page_extractor/extraction_context.py
doc_page_extractor/extractor.py
doc_page_extractor/injection.py
doc_page_extractor/model.py
doc_page_extractor/parser.py
doc_page_extractor/plot.py
doc_page_extractor/redacter.py
doc_page_extractor/types.py
doc_page_extractor-1.0.12.dist-info/LICENSE
doc_page_extractor-1.0.12.dist-info/METADATA
doc_page_extractor-1.0.12.dist-info/WHEEL
doc_page_extractor-1.0.12.dist-info/RECORD
