Metadata-Version: 2.3
Name: doc-page-extractor
Version: 1.0.12
Summary: Document page extraction tool powered by DeepSeek-OCR
License: MIT
Author: Tao Zeyu
Author-email: i@taozeyu.com
Maintainer: Tao Zeyu
Maintainer-email: i@taozeyu.com
Requires-Python: >=3.10,<3.14
Classifier: Development Status :: 2 - Pre-Alpha
Classifier: Intended Audience :: Developers
Classifier: License :: OSI Approved :: MIT License
Classifier: Programming Language :: Python
Classifier: Programming Language :: Python :: 3.10
Classifier: Programming Language :: Python :: 3.11
Classifier: Programming Language :: Python :: 3.12
Classifier: Programming Language :: Python :: 3.13
Requires-Dist: accelerate (>=0.26.0)
Requires-Dist: addict (>=2.4.0)
Requires-Dist: easydict (>=1.13)
Requires-Dist: einops (>=0.8.0)
Requires-Dist: readerwriterlock (>=1.0.9,<2.0.0)
Requires-Dist: transformers (>=4.46.0,<4.48.0)
Project-URL: Repository, https://github.com/moskize91/doc-page-extractor
